ncm/__init__.py
ncm/ncm.py
ncm-0.0.65.dist-info/licenses/LICENSE
ncm-0.0.65.dist-info/METADATA
ncm-0.0.65.dist-info/WHEEL
ncm-0.0.65.dist-info/top_level.txt
ncm-0.0.65.dist-info/RECORD
