Metadata-Version: 2.4
Name: ncm
Version: 0.0.65
Summary: Python client library for Cradlepoint NCM API
Home-page: https://github.com/cradlepoint/api-samples/tree/master/ncm
Author: Nathan Wiens - Cradlepoint
Author-email: nathan.wiens@cradlepoint.com
Requires-Python: >=3.6
License-File: LICENSE
Requires-Dist: requests
Requires-Dist: urllib3
Dynamic: author
Dynamic: author-email
Dynamic: description
Dynamic: description-content-type
Dynamic: home-page
Dynamic: license-file
Dynamic: requires-dist
Dynamic: requires-python
Dynamic: summary
